{
  "updated_at": "2026-07-21T00:36:20+09:00",
  "disclaimer": "이 목록은 공개 시세 데이터(거래량, 변동률)를 기준으로 자동 정렬한 결과이며 특정 종목의 매수/매도를 추천하지 않습니다. 투자 판단과 책임은 본인에게 있습니다.",
  "criteria": {
    "min_price": 5.0,
    "min_avg_volume_3m": 500000,
    "sources": [
      "day_gainers",
      "most_actives"
    ]
  },
  "candidates": [
    {
      "symbol": "IREN",
      "name": "IREN LIMITED",
      "price": 39.1,
      "change_percent": 16.3,
      "volume": 39623332,
      "avg_volume_3m": 46823588,
      "relative_volume": 0.85,
      "market_cap": 13973506048,
      "exchange": "NasdaqGS",
      "sources": [
        "most_actives"
      ],
      "reason": "장중 +16.3% 상승, 거래량 3개월 평균 대비 0.8배, 거래대금 상위 종목",
      "score": 13.79
    },
    {
      "symbol": "ACHR",
      "name": "Archer Aviation Inc.",
      "price": 5.045,
      "change_percent": 13.63,
      "volume": 34328811,
      "avg_volume_3m": 42036345,
      "relative_volume": 0.82,
      "market_cap": 3848653568,
      "exchange": "NYSE",
      "sources": [
        "most_actives"
      ],
      "reason": "장중 +13.6% 상승, 거래량 3개월 평균 대비 0.8배, 거래대금 상위 종목",
      "score": 11.13
    },
    {
      "symbol": "CIFR",
      "name": "Cipher Digital Inc.",
      "price": 20.1,
      "change_percent": 14.46,
      "volume": 17682087,
      "avg_volume_3m": 24969968,
      "relative_volume": 0.71,
      "market_cap": 8221888512,
      "exchange": "NasdaqGS",
      "sources": [
        "most_actives"
      ],
      "reason": "장중 +14.5% 상승, 거래량 3개월 평균 대비 0.7배, 거래대금 상위 종목",
      "score": 10.24
    },
    {
      "symbol": "NUVB",
      "name": "Nuvation Bio Inc.",
      "price": 6.425,
      "change_percent": 10.78,
      "volume": 5795077,
      "avg_volume_3m": 6102901,
      "relative_volume": 0.95,
      "market_cap": 2237197824,
      "exchange": "NYSE",
      "sources": [
        "day_gainers"
      ],
      "reason": "장중 +10.8% 상승, 거래량 3개월 평균 대비 0.9배",
      "score": 10.23
    },
    {
      "symbol": "CLSK",
      "name": "CleanSpark, Inc.",
      "price": 14.485,
      "change_percent": 11.17,
      "volume": 12850609,
      "avg_volume_3m": 22707413,
      "relative_volume": 0.57,
      "market_cap": 3716975616,
      "exchange": "NasdaqCM",
      "sources": [
        "most_actives"
      ],
      "reason": "장중 +11.2% 상승, 거래량 3개월 평균 대비 0.6배, 거래대금 상위 종목",
      "score": 6.32
    },
    {
      "symbol": "MARA",
      "name": "MARA Holdings, Inc.",
      "price": 11.7499,
      "change_percent": 9.91,
      "volume": 18936070,
      "avg_volume_3m": 43374609,
      "relative_volume": 0.44,
      "market_cap": 4479889920,
      "exchange": "NasdaqCM",
      "sources": [
        "most_actives"
      ],
      "reason": "장중 +9.9% 상승, 거래량 3개월 평균 대비 0.4배, 거래대금 상위 종목",
      "score": 4.33
    },
    {
      "symbol": "ONDS",
      "name": "Ondas Inc",
      "price": 6.895,
      "change_percent": 5.67,
      "volume": 51420123,
      "avg_volume_3m": 76383698,
      "relative_volume": 0.67,
      "market_cap": 3929037056,
      "exchange": "NasdaqCM",
      "sources": [
        "most_actives"
      ],
      "reason": "장중 +5.7% 상승, 거래량 3개월 평균 대비 0.7배, 거래대금 상위 종목",
      "score": 3.82
    },
    {
      "symbol": "APLD",
      "name": "Applied Digital Corporation",
      "price": 27.76,
      "change_percent": 7.64,
      "volume": 10554235,
      "avg_volume_3m": 21884495,
      "relative_volume": 0.48,
      "market_cap": 7932962304,
      "exchange": "NasdaqGS",
      "sources": [
        "most_actives"
      ],
      "reason": "장중 +7.6% 상승, 거래량 3개월 평균 대비 0.5배, 거래대금 상위 종목",
      "score": 3.68
    },
    {
      "symbol": "BETA",
      "name": "Beta Technologies, Inc.",
      "price": 18.915,
      "change_percent": 6.5,
      "volume": 835517,
      "avg_volume_3m": 1580322,
      "relative_volume": 0.53,
      "market_cap": 4525555712,
      "exchange": "NYSE",
      "sources": [
        "day_gainers"
      ],
      "reason": "장중 +6.5% 상승, 거래량 3개월 평균 대비 0.5배",
      "score": 3.44
    },
    {
      "symbol": "SLS",
      "name": "SELLAS Life Sciences Group, Inc",
      "price": 12.37,
      "change_percent": -6.22,
      "volume": 4694503,
      "avg_volume_3m": 9468393,
      "relative_volume": 0.5,
      "market_cap": 2432344832,
      "exchange": "NasdaqCM",
      "sources": [
        "day_gainers"
      ],
      "reason": "장중 -6.2% 하락, 거래량 3개월 평균 대비 0.5배",
      "score": 3.08
    },
    {
      "symbol": "TRVI",
      "name": "Trevi Therapeutics, Inc.",
      "price": 17.86,
      "change_percent": -6.35,
      "volume": 895983,
      "avg_volume_3m": 2042808,
      "relative_volume": 0.44,
      "market_cap": 2535757824,
      "exchange": "NasdaqGM",
      "sources": [
        "day_gainers"
      ],
      "reason": "장중 -6.3% 하락, 거래량 3개월 평균 대비 0.4배",
      "score": 2.78
    },
    {
      "symbol": "AXTI",
      "name": "AXT Inc",
      "price": 49.215,
      "change_percent": 7.32,
      "volume": 3778429,
      "avg_volume_3m": 10312960,
      "relative_volume": 0.37,
      "market_cap": 3219802112,
      "exchange": "NasdaqGS",
      "sources": [
        "day_gainers"
      ],
      "reason": "장중 +7.3% 상승, 거래량 3개월 평균 대비 0.4배",
      "score": 2.68
    },
    {
      "symbol": "NBIS",
      "name": "Nebius Group N.V.",
      "price": 187.05,
      "change_percent": 5.26,
      "volume": 8407485,
      "avg_volume_3m": 17837965,
      "relative_volume": 0.47,
      "market_cap": 47491657728,
      "exchange": "NasdaqGS",
      "sources": [
        "day_gainers"
      ],
      "reason": "장중 +5.3% 상승, 거래량 3개월 평균 대비 0.5배",
      "score": 2.48
    },
    {
      "symbol": "SBLK",
      "name": "Star Bulk Carriers Corp.",
      "price": 26.26,
      "change_percent": 5.46,
      "volume": 565031,
      "avg_volume_3m": 1253104,
      "relative_volume": 0.45,
      "market_cap": 2928802304,
      "exchange": "NasdaqGS",
      "sources": [
        "day_gainers"
      ],
      "reason": "장중 +5.5% 상승, 거래량 3개월 평균 대비 0.5배",
      "score": 2.46
    },
    {
      "symbol": "WULF",
      "name": "TeraWulf Inc.",
      "price": 19.16,
      "change_percent": 5.51,
      "volume": 13604005,
      "avg_volume_3m": 31340165,
      "relative_volume": 0.43,
      "market_cap": 9494405120,
      "exchange": "NasdaqCM",
      "sources": [
        "day_gainers"
      ],
      "reason": "장중 +5.5% 상승, 거래량 3개월 평균 대비 0.4배",
      "score": 2.39
    }
  ]
}